applications_archetype/core/__init__.py
applications_archetype/core/commons.py
applications_archetype/core/environments.py
applications_archetype/core/event/__init__.py
applications_archetype/core/event/commons.py
applications_archetype/infrastructure/__init__.py
applications_archetype/infrastructure/db/__init__.py
applications_archetype/infrastructure/db/database.py
applications_archetype/infrastructure/http/__init__.py
applications_archetype/infrastructure/http/commons.py
applications_archetype/infrastructure/http/configs.py
applications_archetype/infrastructure/http/errors.py
applications_archetype/infrastructure/http/events.py
applications_archetype/infrastructure/http/responses.py
applications_elprat-0.0.4.dist-info/licenses/LICENSE
applications_elprat-0.0.4.dist-info/METADATA
applications_elprat-0.0.4.dist-info/WHEEL
applications_elprat-0.0.4.dist-info/top_level.txt
applications_elprat-0.0.4.dist-info/RECORD
