Metadata-Version: 2.4
Name: applications-elprat
Version: 0.0.4
Summary: A Python library for applications and reusable structure for future projects of the town hall of l'prat
Author-email: Yovany Dominico Girón <y.dominico.giron@elprat.cat>
Maintainer-email: Yovany Dominico Girón <y.dominico.giron@elprat.cat>
Classifier: Programming Language :: Python :: 3
Classifier: Operating System :: OS Independent
Classifier: Development Status :: 3 - Alpha
Classifier: Framework :: FastAPI
Requires-Python: >=3.11.11
License-File: LICENSE
Requires-Dist: click>=8.1.7
Requires-Dist: jinja2>=3.1.5
Requires-Dist: Faker>=33.3.0
Requires-Dist: fastapi>=0.115.5
Requires-Dist: SQLAlchemy>=2.0.36
Requires-Dist: pytest>=8.3.4
Requires-Dist: virtualenv>=20.27.1
Requires-Dist: jsonschema>=4.23.0
Requires-Dist: orjson>=3.10.13
Dynamic: license-file
